{
  "active": true,
  "started_at": "2026-03-05T01:05:20.536Z",
  "original_prompt": "em producao ele continua enviando para o checkout. pode ser limitacao da vercel, mas deve ser alguma coisa do backend que voce esqueceu. apos o login crie uma pagina de bem vindo e garanta que tenha o acesso. é algo simples, nao tem porque voce errar tanto, use ralph loop para garantir correcao",
  "session_id": "f3951d98-07a1-4282-aa74-f7da6c62b21c",
  "reinforcement_count": 0,
  "last_checked_at": "2026-03-05T01:23:46.160Z",
  "iteration": 4
}